[
  {
    "image": "/rice and parripu curry.jpg",
    "product_name": "Parippu & Rice Combo",
    "malayalam_name": "പരിപ്പ് കറി",
    "price": 70.00,
    "category": "veg Combo",
    "description": "Grilled fish fillet with steamed rice and vegetables",
    "rating": 4.6,
    "prep_time": "20-25 min"
  },
  {
    "image": "/porotta sambar.jpg",
    "product_name": "Parotta Sambar",
    "malayalam_name": "പൊറോട്ട സാമ്പാർ",
    "price": 30.00,
    "category": "veg Combo",
    "description": "Steamed rice with chicken curry and naan bread",
    "rating": 4.5,
    "prep_time": "20-25 min"
  },
  {
    "image": "/rice and parripu curry.jpg",
    "product_name": "Parippu & Rice Combo",
    "malayalam_name": "പരിപ്പ് കറി",
    "price": 70.00,
    "category": "veg Combo",
    "description": "Grilled fish fillet with steamed rice and vegetables",
    "rating": 4.6,
    "prep_time": "20-25 min"
  },
  {
    "image": "/veg.png",
    "product_name": "Dal Khichdi & Pickle",
    "malayalam_name": "ദാൽ ഖിച്ചഡി ആൻഡ് പിക്കിൾ",
    "price": 14.75,
    "category": "Veg Combo",
    "description": "Comforting dal khichdi with tangy pickle and ghee",
    "rating": 4.2,
    "prep_time": "20-25 min"
  },
  {
    "image": "/veg.png",
    "product_name": "Veg Thali Special",
    "malayalam_name": "വെജ് താളി സ്പെഷൽ",
    "price": 25.99,
    "category": "Veg Combo",
    "description": "Complete veg thali with 3 curries, rice, roti, and dessert",
    "rating": 4.7,
    "prep_time": "30-35 min"
  }
] 